syft_crypto/__init__.py
syft_crypto/did_utils.py
syft_crypto/key_storage.py
syft_crypto/x3dh.py
syft_crypto/x3dh_bootstrap.py
syft_crypto-0.1.2.dist-info/METADATA
syft_crypto-0.1.2.dist-info/WHEEL
syft_crypto-0.1.2.dist-info/RECORD
