Metadata-Version: 2.4
Name: syft-crypto
Version: 0.1.2
Summary: End-to-end encryption utilities for SyftBox using X3DH protocol
Requires-Python: >=3.9
Requires-Dist: cryptography<45.0.0,>=44.0.1
Requires-Dist: jwcrypto>=1.5.0
Requires-Dist: loguru>=0.7.2
Requires-Dist: pydantic>=2.0.0
Requires-Dist: syft-core>=0.3.0
